botbond/__init__.py
botbond/classes/__init__.py
botbond/classes/channels.py
botbond/modules/__init__.py
botbond/modules/server.py
botbond/plugins/__init__.py
botbond/plugins/hipchat.py
botbond/plugins/slack.py
botbond-0.18.data/scripts/botbond
botbond-0.18.dist-info/DESCRIPTION.rst
botbond-0.18.dist-info/METADATA
botbond-0.18.dist-info/RECORD
botbond-0.18.dist-info/WHEEL
botbond-0.18.dist-info/metadata.json
botbond-0.18.dist-info/top_level.txt
