Metadata-Version: 2.0
Name: botbond
Version: 0.18
Summary: botbond
Home-page: https://github.com/decryptus/botbond
Author: Adrien Delle Cave
Author-email: pypi@doowan.net
License: License GPL-2
Platform: UNKNOWN
Requires-Dist: dwho (>=0.2.89)
Requires-Dist: emoji
Requires-Dist: httpdis (>=0.5.13)
Requires-Dist: hypchat
Requires-Dist: pyyaml (>=3.10)
Requires-Dist: redis (>=2.4.0)
Requires-Dist: requests
Requires-Dist: slackclient
Requires-Dist: sonicprobe (>=0.2.70)
